{"cameraMode":{"drawMode":0,"name":"Shaded","section":"Shading Mode"},"sceneLighting":true,"audioPlay":false,"sceneViewState":{"m_AlwaysRefresh":false,"showFog":true,"showSkybox":true,"showFlares":true,"showImageEffects":true,"showParticleSystems":true,"showVisualEffectGraphs":true,"m_FxEnabled":true},"in2DMode":false,"pivot":{"x":-7.889339447021484,"y":-9.368295669555664,"z":1.9995718002319337},"rotation":{"x":-0.09425412863492966,"y":-0.8944374322891235,"z":0.224873349070549,"w":-0.37489017844200137},"size":52.89561462402344,"orthographic":false}